functions_by_marieane22/README.md
functions_by_marieane22/math_functions.py
functions_by_marieane22-0.4.0.dist-info/WHEEL
functions_by_marieane22-0.4.0.dist-info/METADATA
functions_by_marieane22-0.4.0.dist-info/RECORD
