Metadata-Version: 2.1
Name: functions-by-marieane22
Version: 0.4.0
Summary: This is a test project.
Author: marieane22
Author-email: marieane@live.com
Requires-Python: >=3.10,<4.0
Classifier: Programming Language :: Python :: 3
Classifier: Programming Language :: Python :: 3.10
Classifier: Programming Language :: Python :: 3.11
